<Loadout>
  <Items>
    <Item portName="Body_ItemPort" itemName="body_01" tag="Char_Body">
      <Items>
        <Item portName="Head_ItemPort" itemName="PU_Protos_Head" tag="Char_Head(Male)">
          <Items>
            <Item portName="Teeth_ItemPort" itemName="Head_Teeth" tag="Char_Accessory_Head" />
            <Item portName="Eyes_ItemPort" itemName="Head_Eyes_Brown_03">
              <Items>
                <Item portName="Lens_ItemPort" itemName="Default_LensDisplay" />
              </Items>
            </Item>
            <Item portName="Hair_ItemPort" itemName="bald_hair_01" tag="Char_Head_Hair Male" />
            <Item portName="Eyelashes_ItemPort" itemName="Head_Eyelashes" tag="Char_Head_Hair(EyeWare)" />
            <Item portName="Eyebrow_ItemPort" itemName="Shared_Brows_Unified" tag="Char_Head_Eyebrow" />
            <Item portName="Skin_Variant" itemName="Skin_Var_08" />
          </Items>
        </Item>
      </Items>
    </Item>
  </Items>
</Loadout>