<HarvestablePreset.Mining_AsteroidCType_Copper entityClass="01b977c8-467f-4be7-94e9-b4b9843dd700" respawnInSlotTime="3600" specialHarvestableString="" __type="HarvestablePreset" __ref="9a515797-21a3-469f-9f50-b905d09e84b5" __path="libs/foundry/records/harvestable/harvestablepresets/mining_asteroidctype_copper.xml">
  <harvestBehaviour __type="HarvestBehaviourParams">
    <harvestConditions>
      <HarvestConditionHealth healthRatio="0" __type="HarvestConditionBase" __polymorphicType="HarvestConditionHealth" />
    </harvestConditions>
    <despawnTimer despawnTimeSeconds="600" additionalWaitForNearbyPlayersSeconds="300" __type="HarvestDespawnTimerParams" />
  </harvestBehaviour>
  <transformParams minScale="0.2" maxScale="1" terrainNormalAlignment="1" minZOffset="0.1" maxZOffset="0.25" minSlope="0" maxSlope="90" minElevation="-10000" maxElevation="10000" __type="HarvestableTransformParams">
    <rotationRange x="360" y="360" z="360" __type="Vec3" />
  </transformParams>
  <subConfigBase>
  </subConfigBase>
</HarvestablePreset.Mining_AsteroidCType_Copper>