<TacticalQuery.RandomPositionsInArea name="RandomPositionsInArea" type="TacticalPointQuery" __type="TacticalQuery" __ref="9aa8f09c-5ab7-45aa-9aa9-2167db4f584b" __path="libs/foundry/records/tacticalquery/tpsqueries/groundcombatqueries/randompositionsinarea.xml">
  <options>
    <TQSEmbeddedOption __type="TQSOption" __polymorphicType="TQSEmbeddedOption">
      <requirements __type="TagsDNF">
        <terms />
      </requirements>
      <content __type="TQSOptionContent">
        <parameters>
          <TQSInputFloatValue condition="density" value="1.2" __type="TQSInput" __polymorphicType="TQSInputFloatValue">
            <requirements __type="TagsDNF">
              <terms />
            </requirements>
            <overrides />
          </TQSInputFloatValue>
        </parameters>
        <generation>
          <TQSInputFloatValue condition="grid_around_referencePoint" value="10" __type="TQSInput" __polymorphicType="TQSInputFloatValue">
            <requirements __type="TagsDNF">
              <terms />
            </requirements>
            <overrides />
          </TQSInputFloatValue>
        </generation>
        <conditions>
          <TQSInputFloatValue condition="min_distance_to_puppet" value="1" __type="TQSInput" __polymorphicType="TQSInputFloatValue">
            <requirements __type="TagsDNF">
              <terms />
            </requirements>
            <overrides />
          </TQSInputFloatValue>
          <TQSInputBoolValue condition="isPointReachable_from_puppet" value="1" __type="TQSInput" __polymorphicType="TQSInputBoolValue">
            <requirements __type="TagsDNF">
              <terms />
            </requirements>
            <overrides />
          </TQSInputBoolValue>
          <TQSInputBoolValue condition="isInside_of_area" value="1" __type="TQSInput" __polymorphicType="TQSInputBoolValue">
            <requirements __type="TagsDNF">
              <terms />
            </requirements>
            <overrides />
          </TQSInputBoolValue>
          <TQSInputBoolValue condition="isPositionReserved" value="0" __type="TQSInput" __polymorphicType="TQSInputBoolValue">
            <requirements __type="TagsDNF">
              <terms />
            </requirements>
            <overrides />
          </TQSInputBoolValue>
        </conditions>
        <weights>
          <TQSWeightInputValue condition="random" weight="0.2" __type="TQSInput" __polymorphicType="TQSWeightInputValue">
            <requirements __type="TagsDNF">
              <terms />
            </requirements>
            <overrides />
          </TQSWeightInputValue>
          <TQSWeightInputValue condition="friendlyDistance" weight="0.5" __type="TQSInput" __polymorphicType="TQSWeightInputValue">
            <requirements __type="TagsDNF">
              <terms />
            </requirements>
            <overrides />
          </TQSWeightInputValue>
          <TQSWeightInputValue condition="friendlyReservedPositionsDistance" weight="0.5" __type="TQSInput" __polymorphicType="TQSWeightInputValue">
            <requirements __type="TagsDNF">
              <terms />
            </requirements>
            <overrides />
          </TQSWeightInputValue>
          <TQSWeightInputValue condition="distance_to_puppet" weight="-0.75" __type="TQSInput" __polymorphicType="TQSWeightInputValue">
            <requirements __type="TagsDNF">
              <terms />
            </requirements>
            <overrides />
          </TQSWeightInputValue>
        </weights>
      </content>
      <optionOverrides />
    </TQSEmbeddedOption>
  </options>
</TacticalQuery.RandomPositionsInArea>